datachallenge/scripts/format_metrics.py
datachallenge/scripts/wrap_yaml.py
docs/tmp/ocb_dc_ose_2021_data.py
oost_dc_ose_2021/__init__.py
oost_dc_ose_2021/mods/__init__.py
oost_dc_ose_2021/mods/cmems_get.py
oost_dc_ose_2021/mods/interp_on_track.py
oost_dc_ose_2021/mods/lambdax.py
oost_dc_ose_2021/mods/mu.py
oost_dc_ose_2021/mods/prepare_track.py
oost_dc_ose_2021/pipelines/__init__.py
oost_dc_ose_2021/pipelines/input_data.py
oost_dc_ose_2021/pipelines/metrics.py
oost_demo_ssh_dc-2024.4.15.1621.dist-info/LICENSE
oost_demo_ssh_dc-2024.4.15.1621.dist-info/METADATA
oost_demo_ssh_dc-2024.4.15.1621.dist-info/WHEEL
oost_demo_ssh_dc-2024.4.15.1621.dist-info/entry_points.txt
oost_demo_ssh_dc-2024.4.15.1621.dist-info/top_level.txt
oost_demo_ssh_dc-2024.4.15.1621.dist-info/RECORD
